ca_certificates/__init__.py
cugraph_service_server-0.0.1.dist-info/METADATA
cugraph_service_server-0.0.1.dist-info/WHEEL
cugraph_service_server-0.0.1.dist-info/top_level.txt
cugraph_service_server-0.0.1.dist-info/RECORD
