Metadata-Version: 2.4
Name: cugraph-service-server
Version: 0.0.1
Summary: Dummy cugraph-service-server package for PyPI
Author-email: Your Name <you@example.com>
Requires-Python: >=3.7
